{
  "updated_at": "2026-04-23T01:50:29",
  "failed_sources": [
    {
      "name": "워크넷",
      "url": "https://www.work.go.kr",
      "reason": "0건 수집"
    },
    {
      "name": "금융위원회",
      "url": "https://www.fsc.go.kr",
      "reason": "수집 실패: ('Connection aborted.', ConnectionResetError(104, 'Connection reset by peer'))"
    },
    {
      "name": "복지로",
      "url": "https://www.bokjiro.go.kr",
      "reason": "수집 실패: ('Connection aborted.', ConnectionResetError(104, 'Connection reset by peer'))"
    },
    {
      "name": "부산청년포털",
      "url": "https://youth.busan.go.kr",
      "reason": "0건 수집"
    }
  ],
  "items": [
    {
      "id": "alio_65b0cd1b93",
      "category": "채용",
      "subcategory": "채용",
      "title": "국립암센터",
      "org": "경기",
      "deadline": "2026-04-23",
      "url": "https://job.alio.go.kr/recruitview.do?idx=299640",
      "source": "잡알리오",
      "region": "전국",
      "is_new": true
    },
    {
      "id": "jobkorea_b0c7751b7a",
      "category": "채용",
      "subcategory": "인턴",
      "title": "금융컨설팅부문 PI(프로세스 개선) 컨설팅 인턴",
      "org": "한영회계법인",
      "deadline": "2026-04-23",
      "url": "https://www.jobkorea.co.kr/Recruit/GI_Read/49020367?Oem_Code=C1&logpath=1&stext=%EA%B8%88%EC%9C%B5+%EC%9D%B8%ED%84%B4&listno=9&sc=630",
      "source": "잡코리아",
      "region": "전국",
      "is_new": true
    },
    {
      "id": "alio_f991a80c05",
      "category": "채용",
      "subcategory": "인턴",
      "title": "코레일테크(주)",
      "org": "서울 외 2",
      "deadline": "2026-04-23",
      "url": "https://job.alio.go.kr/recruitview.do?idx=299604",
      "source": "잡알리오",
      "region": "전국",
      "is_new": true
    },
    {
      "id": "alio_fce38823b2",
      "category": "채용",
      "subcategory": "채용",
      "title": "한국국제보건의료재단",
      "org": "서울 외 1",
      "deadline": "2026-04-23",
      "url": "https://job.alio.go.kr/recruitview.do?idx=299636",
      "source": "잡알리오",
      "region": "전국",
      "is_new": true
    },
    {
      "id": "alio_9933375935",
      "category": "채용",
      "subcategory": "채용",
      "title": "한국농업기술진흥원",
      "org": "전북",
      "deadline": "2026-04-23",
      "url": "https://job.alio.go.kr/recruitview.do?idx=299637",
      "source": "잡알리오",
      "region": "전국",
      "is_new": false
    },
    {
      "id": "alio_1b5c43a2c3",
      "category": "채용",
      "subcategory": "채용",
      "title": "한국산업인력공단",
      "org": "전북",
      "deadline": "2026-04-23",
      "url": "https://job.alio.go.kr/recruitview.do?idx=299638",
      "source": "잡알리오",
      "region": "전국",
      "is_new": true
    },
    {
      "id": "alio_280016986d",
      "category": "채용",
      "subcategory": "채용",
      "title": "한국토지주택공사",
      "org": "강원",
      "deadline": "2026-04-23",
      "url": "https://job.alio.go.kr/recruitview.do?idx=299641",
      "source": "잡알리오",
      "region": "전국",
      "is_new": true
    },
    {
      "id": "alio_e525569010",
      "category": "채용",
      "subcategory": "채용",
      "title": "한전KDN",
      "org": "충남",
      "deadline": "2026-04-23",
      "url": "https://job.alio.go.kr/recruitview.do?idx=299603",
      "source": "잡알리오",
      "region": "전국",
      "is_new": false
    },
    {
      "id": "alio_f88d737322",
      "category": "채용",
      "subcategory": "채용",
      "title": "한전KPS(주)",
      "org": "충북",
      "deadline": "2026-04-23",
      "url": "https://job.alio.go.kr/recruitview.do?idx=299615",
      "source": "잡알리오",
      "region": "전국",
      "is_new": false
    },
    {
      "id": "youthdb_a594840d0c",
      "category": "채용",
      "subcategory": "인턴",
      "title": "2026년 1차 고용노동부 대구지방고용노동청 청년인턴 채용 공고(재공고)",
      "org": "고용노동부",
      "deadline": "2026-04-28",
      "url": "https://www.2030db.go.kr/user/youthIntern/selectYouthInternDetail.do?youthId=INTERN_0000000031987",
      "source": "청년인재DB",
      "region": "전국",
      "is_new": false
    },
    {
      "id": "jobkorea_cdd7c80577",
      "category": "채용",
      "subcategory": "인턴",
      "title": "[대만인] 유튜브 금융 콘텐츠 기획PD (인턴,계약직)",
      "org": "어스얼라이언스㈜",
      "deadline": "2026-04-30",
      "url": "https://www.jobkorea.co.kr/Recruit/GI_Read/48781792?Oem_Code=C1&logpath=1&stext=%EA%B8%88%EC%9C%B5+%EC%9D%B8%ED%84%B4&listno=10&sc=630",
      "source": "잡코리아",
      "region": "전국",
      "is_new": true
    },
    {
      "id": "jobkorea_6c4f60cea7",
      "category": "채용",
      "subcategory": "인턴",
      "title": "각 부문별 경력직 채용 - ETF LP",
      "org": "㈜아이엠증권",
      "deadline": "2026-04-30",
      "url": "https://www.jobkorea.co.kr/Recruit/GI_Read/49026745?Oem_Code=C1&logpath=1&stext=%EA%B8%88%EC%9C%B5+%EC%9D%B8%ED%84%B4&listno=15&sc=630",
      "source": "잡코리아",
      "region": "전국",
      "is_new": true
    },
    {
      "id": "jobkorea_2acd9dc5e9",
      "category": "채용",
      "subcategory": "인턴",
      "title": "각 부문별 신입/경력직 채용",
      "org": "㈜아이엠증권",
      "deadline": "2026-04-30",
      "url": "https://www.jobkorea.co.kr/Recruit/GI_Read/49026723?Oem_Code=C1&logpath=1&stext=%EA%B8%88%EC%9C%B5+%EC%9D%B8%ED%84%B4&listno=16&sc=630",
      "source": "잡코리아",
      "region": "전국",
      "is_new": true
    },
    {
      "id": "jobkorea_2e7e26e52a",
      "category": "채용",
      "subcategory": "인턴",
      "title": "인카금융서비스(주) 영업 신입/경력/관리자 모집",
      "org": "인카금융서비스",
      "deadline": "2026-05-03",
      "url": "https://www.jobkorea.co.kr/Recruit/GI_Read/48906329?Oem_Code=C1&logpath=1&stext=%EA%B8%88%EC%9C%B5+%EC%9D%B8%ED%84%B4&listno=14&sc=630",
      "source": "잡코리아",
      "region": "전국",
      "is_new": true
    },
    {
      "id": "jobkorea_41d9ef8727",
      "category": "채용",
      "subcategory": "인턴",
      "title": "그래비티벤처스 AC본부 채용 전환형 인턴 모집",
      "org": "㈜그래비티벤처스",
      "deadline": "2026-05-08",
      "url": "https://www.jobkorea.co.kr/Recruit/GI_Read/48940424?Oem_Code=C1&logpath=1&stext=%EA%B8%88%EC%9C%B5+%EC%9D%B8%ED%84%B4&listno=7&sc=630",
      "source": "잡코리아",
      "region": "전국",
      "is_new": true
    },
    {
      "id": "jobkorea_8afe65aa87",
      "category": "채용",
      "subcategory": "체험형 인턴",
      "title": "[DB증권] 본사 업무직 인턴십(체험형 인턴) 모집",
      "org": "디비증권㈜",
      "deadline": "2026-05-11",
      "url": "https://www.jobkorea.co.kr/Recruit/GI_Read/49035348?Oem_Code=C1&logpath=1&stext=%EA%B8%88%EC%9C%B5+%EC%9D%B8%ED%84%B4&listno=13&sc=630",
      "source": "잡코리아",
      "region": "전국",
      "is_new": true
    },
    {
      "id": "jobkorea_41799a9cc1",
      "category": "채용",
      "subcategory": "인턴",
      "title": "참저축은행 여신업무 직원 채용",
      "org": "㈜참저축은행",
      "deadline": "2026-05-13",
      "url": "https://www.jobkorea.co.kr/Recruit/GI_Read/49029830?Oem_Code=C1&logpath=1&stext=%EA%B8%88%EC%9C%B5+%EC%9D%B8%ED%84%B4&listno=12&sc=630",
      "source": "잡코리아",
      "region": "전국",
      "is_new": true
    },
    {
      "id": "jobkorea_4e21092812",
      "category": "채용",
      "subcategory": "인턴",
      "title": "[인턴/업무팀] 적하보험 증권 발급 사무직 채용",
      "org": "㈜노피곰",
      "deadline": "2026-05-17",
      "url": "https://www.jobkorea.co.kr/Recruit/GI_Read/49004815?Oem_Code=C1&logpath=1&stext=%EA%B8%88%EC%9C%B5+%EC%9D%B8%ED%84%B4&listno=6&sc=630",
      "source": "잡코리아",
      "region": "전국",
      "is_new": true
    },
    {
      "id": "jobkorea_0db7a976ad",
      "category": "채용",
      "subcategory": "인턴",
      "title": "[빗썸] 총무 지원 (인턴, 6개월 계약직)",
      "org": "주식회사 빗썸",
      "deadline": "2026-05-19",
      "url": "https://www.jobkorea.co.kr/Recruit/GI_Read/48816087?Oem_Code=C1&logpath=1&stext=%EA%B8%88%EC%9C%B5+%EC%9D%B8%ED%84%B4&listno=2&sc=630",
      "source": "잡코리아",
      "region": "전국",
      "is_new": false
    },
    {
      "id": "jobkorea_f5dea57213",
      "category": "채용",
      "subcategory": "인턴",
      "title": "기업투자본부 인턴 채용",
      "org": "유진자산운용㈜",
      "deadline": "2026-05-22",
      "url": "https://www.jobkorea.co.kr/Recruit/GI_Read/49037170?Oem_Code=C1&logpath=1&stext=%EA%B8%88%EC%9C%B5+%EC%9D%B8%ED%84%B4&listno=19&sc=630",
      "source": "잡코리아",
      "region": "전국",
      "is_new": true
    },
    {
      "id": "jobkorea_f1aa20f7b6",
      "category": "채용",
      "subcategory": "인턴",
      "title": "벤처캐피탈 투자 본부 인턴(산업 리서치 ,IM 및 티저 작성 보조)",
      "org": "㈜송현인베스트먼트",
      "deadline": "2026-05-22",
      "url": "https://www.jobkorea.co.kr/Recruit/GI_Read/49032780?Oem_Code=C1&logpath=1&stext=%EA%B8%88%EC%9C%B5+%EC%9D%B8%ED%84%B4&listno=4&sc=630",
      "source": "잡코리아",
      "region": "전국",
      "is_new": true
    },
    {
      "id": "jobkorea_e545b10bee",
      "category": "채용",
      "subcategory": "인턴",
      "title": "[고객관리 영업사원 본사직영] 신입 및 경력사원 / 대면영업&복합채널 보험설계사 채용",
      "org": "㈜미래전략금융서비스",
      "deadline": "2026-06-09",
      "url": "https://www.jobkorea.co.kr/Recruit/GI_Read/48956837?Oem_Code=C1&logpath=1&stext=%EA%B8%88%EC%9C%B5+%EC%9D%B8%ED%84%B4&listno=4&sc=552",
      "source": "잡코리아",
      "region": "부산",
      "is_new": true
    },
    {
      "id": "jobkorea_15d7f53f9a",
      "category": "채용",
      "subcategory": "인턴",
      "title": "더베스트금융 인스금융사업단 관리지점장/매니저 채용(경력 평택/수원)",
      "org": "더베스트금융서비스㈜",
      "deadline": "2026-06-12",
      "url": "https://www.jobkorea.co.kr/Recruit/GI_Read/48967970?Oem_Code=C1&logpath=1&stext=%EA%B8%88%EC%9C%B5+%EC%9D%B8%ED%84%B4&listno=3&sc=552",
      "source": "잡코리아",
      "region": "전국",
      "is_new": true
    },
    {
      "id": "youth_0e5621c6b8",
      "category": "지원금",
      "subcategory": "주거지원",
      "title": "전세보증금 반환보증 보증료 지원",
      "org": "국토교통부",
      "deadline": "2026-07-05",
      "url": "https://www.youthcenter.go.kr/youthPolicy/ythPlcyTotalSearch/ythPlcyDetail/20260413005400212694",
      "source": "온통청년",
      "region": "전국",
      "is_new": false
    },
    {
      "id": "youth_3780ccb1aa",
      "category": "지원금",
      "subcategory": "취업지원",
      "title": "전북특별자치도 일자리센터 운영",
      "org": "전북특별자치도 기업유치지원실 일자리민생경제과",
      "deadline": "2026-12-31",
      "url": "https://www.youthcenter.go.kr/youthPolicy/ythPlcyTotalSearch/ythPlcyDetail/20260319005400212219",
      "source": "온통청년",
      "region": "전국",
      "is_new": false
    },
    {
      "id": "youth_2b75f49129",
      "category": "지원금",
      "subcategory": "취업지원",
      "title": "전북형 청년취업 지원",
      "org": "전북특별자치도",
      "deadline": "2026-12-31",
      "url": "https://www.youthcenter.go.kr/youthPolicy/ythPlcyTotalSearch/ythPlcyDetail/20260331005400212354",
      "source": "온통청년",
      "region": "전국",
      "amount": "월 70만원",
      "is_new": false
    },
    {
      "id": "youth_2574ab844b",
      "category": "지원금",
      "subcategory": "주거지원",
      "title": "전세보증금반환보증 보증료 지원",
      "org": "제주특별자치도경제통상진흥원 경영본부 청년센터",
      "deadline": "2026-12-31",
      "url": "https://www.youthcenter.go.kr/youthPolicy/ythPlcyTotalSearch/ythPlcyDetail/20260421005400212799",
      "source": "온통청년",
      "region": "전국",
      "amount": "최대 40만원",
      "is_new": false
    },
    {
      "id": "youth_869c69e654",
      "category": "지원금",
      "subcategory": "주거지원",
      "title": "제주 청년 희망충전 월세 지원",
      "org": "제주특별자치도경제통상진흥원 경영본부 청년센터",
      "deadline": "2026-12-31",
      "url": "https://www.youthcenter.go.kr/youthPolicy/ythPlcyTotalSearch/ythPlcyDetail/20260422005400212846",
      "source": "온통청년",
      "region": "전국",
      "amount": "월 최대 20만원",
      "is_new": false
    },
    {
      "id": "youth_22ef1f4ae6",
      "category": "지원금",
      "subcategory": "지원사업",
      "title": "제주청년등록시스템 운영",
      "org": "제주특별자치도경제통상진흥원 경영본부 청년센터",
      "deadline": "2026-12-31",
      "url": "https://www.youthcenter.go.kr/youthPolicy/ythPlcyTotalSearch/ythPlcyDetail/20260421005400212829",
      "source": "온통청년",
      "region": "전국",
      "is_new": false
    },
    {
      "id": "youth_0af9a8813e",
      "category": "지원금",
      "subcategory": "취업지원",
      "title": "조선해양 미래혁신인재 양성센터사업",
      "org": "경상남도",
      "deadline": "2026-12-31",
      "url": "https://www.youthcenter.go.kr/youthPolicy/ythPlcyTotalSearch/ythPlcyDetail/20260408005400212583",
      "source": "온통청년",
      "region": "전국",
      "is_new": false
    },
    {
      "id": "youth_ba8a673331",
      "category": "지원금",
      "subcategory": "창업지원",
      "title": "지식재산 기반 창업촉진(IP 디딤돌 프로그램)",
      "org": "한국발명진흥회",
      "deadline": "2026-12-31",
      "url": "https://www.youthcenter.go.kr/youthPolicy/ythPlcyTotalSearch/ythPlcyDetail/20260323005400112245",
      "source": "온통청년",
      "region": "부산",
      "is_new": false
    },
    {
      "id": "youth_c22497a8cb",
      "category": "지원금",
      "subcategory": "지원사업",
      "title": "지역산업 연계형 대학 특성화학과 혁신지원사업",
      "org": "경상북도 메타AI과학국",
      "deadline": "2026-12-31",
      "url": "https://www.youthcenter.go.kr/youthPolicy/ythPlcyTotalSearch/ythPlcyDetail/20260331005400212374",
      "source": "온통청년",
      "region": "전국",
      "is_new": false
    },
    {
      "id": "youth_cd0b7660f6",
      "category": "지원금",
      "subcategory": "지원사업",
      "title": "지역필수의사제 시범사업",
      "org": "경상남도",
      "deadline": "2026-12-31",
      "url": "https://www.youthcenter.go.kr/youthPolicy/ythPlcyTotalSearch/ythPlcyDetail/20260408005400212587",
      "source": "온통청년",
      "region": "전국",
      "is_new": false
    },
    {
      "id": "youth_4401a5480f",
      "category": "지원금",
      "subcategory": "주거지원",
      "title": "창업허브센터 운영",
      "org": "경상북도 의성군 관광복지국",
      "deadline": "2026-12-31",
      "url": "https://www.youthcenter.go.kr/youthPolicy/ythPlcyTotalSearch/ythPlcyDetail/20260330005400212323",
      "source": "온통청년",
      "region": "전국",
      "is_new": false
    },
    {
      "id": "youth_06d4553107",
      "category": "지원금",
      "subcategory": "지원사업",
      "title": "청년 구직활동 지원사업",
      "org": "경상북도 안동시",
      "deadline": "2026-12-31",
      "url": "https://www.youthcenter.go.kr/youthPolicy/ythPlcyTotalSearch/ythPlcyDetail/20260331005400212365",
      "source": "온통청년",
      "region": "전국",
      "is_new": false
    },
    {
      "id": "youth_908df96b32",
      "category": "지원금",
      "subcategory": "창업지원",
      "title": "청년 네트워크 활성화 지원사업",
      "org": "재단법인대전청년내일재단",
      "deadline": "2026-12-31",
      "url": "https://www.youthcenter.go.kr/youthPolicy/ythPlcyTotalSearch/ythPlcyDetail/20260107005400212074",
      "source": "온통청년",
      "region": "전국",
      "is_new": false
    },
    {
      "id": "youth_e0f00200a5",
      "category": "지원금",
      "subcategory": "취업지원",
      "title": "청년 면접 준비비 지원사업",
      "org": "경상북도 경주시 시민복지국",
      "deadline": "2026-12-31",
      "url": "https://www.youthcenter.go.kr/youthPolicy/ythPlcyTotalSearch/ythPlcyDetail/20260320005400212240",
      "source": "온통청년",
      "region": "전국",
      "amount": "최대 20만원",
      "is_new": false
    },
    {
      "id": "youth_dccee2d42e",
      "category": "지원금",
      "subcategory": "생활지원",
      "title": "청년 지역정착 활성화 사업",
      "org": "경상북도 의성군 관광복지국",
      "deadline": "2026-12-31",
      "url": "https://www.youthcenter.go.kr/youthPolicy/ythPlcyTotalSearch/ythPlcyDetail/20260330005400212319",
      "source": "온통청년",
      "region": "부산",
      "is_new": false
    },
    {
      "id": "youth_2be7820bed",
      "category": "지원금",
      "subcategory": "취업지원",
      "title": "청년공간 운영사업",
      "org": "의왕시",
      "deadline": "2026-12-31",
      "url": "https://www.youthcenter.go.kr/youthPolicy/ythPlcyTotalSearch/ythPlcyDetail/20250402005400210683",
      "source": "온통청년",
      "region": "전국",
      "is_new": false
    },
    {
      "id": "youth_c6a4caa167",
      "category": "지원금",
      "subcategory": "지원사업",
      "title": "청년기업 융자지원사업",
      "org": "경상북도 의성군 관광복지국",
      "deadline": "2026-12-31",
      "url": "https://www.youthcenter.go.kr/youthPolicy/ythPlcyTotalSearch/ythPlcyDetail/20260330005400212318",
      "source": "온통청년",
      "region": "부산",
      "is_new": false
    },
    {
      "id": "youth_eeec842814",
      "category": "지원금",
      "subcategory": "주거지원",
      "title": "청년단기주거공간 운영(금강장)",
      "org": "경상북도 의성군 관광복지국",
      "deadline": "2026-12-31",
      "url": "https://www.youthcenter.go.kr/youthPolicy/ythPlcyTotalSearch/ythPlcyDetail/20260325005400212276",
      "source": "온통청년",
      "region": "부산",
      "is_new": false
    },
    {
      "id": "youth_48c5c8c3e9",
      "category": "지원금",
      "subcategory": "취업지원",
      "title": "청년도전지원사업 참여자 모집(전북)",
      "org": "전북특별자치도",
      "deadline": "2026-12-31",
      "url": "https://www.youthcenter.go.kr/youthPolicy/ythPlcyTotalSearch/ythPlcyDetail/20260331005400212353",
      "source": "온통청년",
      "region": "전국",
      "is_new": false
    },
    {
      "id": "youth_98ca4982a8",
      "category": "지원금",
      "subcategory": "주거지원",
      "title": "청년복합주거공간 운영(금수장)",
      "org": "경상북도 의성군 관광복지국",
      "deadline": "2026-12-31",
      "url": "https://www.youthcenter.go.kr/youthPolicy/ythPlcyTotalSearch/ythPlcyDetail/20260325005400212275",
      "source": "온통청년",
      "region": "부산",
      "is_new": false
    },
    {
      "id": "youth_7b77fb9436",
      "category": "지원금",
      "subcategory": "지원사업",
      "title": "청년새마을연대 푸른경북만들기",
      "org": "경상북도 안전행정실 새마을봉사과",
      "deadline": "2026-12-31",
      "url": "https://www.youthcenter.go.kr/youthPolicy/ythPlcyTotalSearch/ythPlcyDetail/20260316005400212164",
      "source": "온통청년",
      "region": "전국",
      "is_new": false
    },
    {
      "id": "youth_bd14ed05bd",
      "category": "지원금",
      "subcategory": "취업지원",
      "title": "청년성장프로젝트",
      "org": "제주특별자치도경제통상진흥원 경영본부 청년센터",
      "deadline": "2026-12-31",
      "url": "https://www.youthcenter.go.kr/youthPolicy/ythPlcyTotalSearch/ythPlcyDetail/20260413005400212723",
      "source": "온통청년",
      "region": "전국",
      "is_new": false
    },
    {
      "id": "youth_7fa9122de5",
      "category": "지원금",
      "subcategory": "주거지원",
      "title": "청년시청 운영",
      "org": "전북특별자치도 익산시 청년경제국",
      "deadline": "2026-12-31",
      "url": "https://www.youthcenter.go.kr/youthPolicy/ythPlcyTotalSearch/ythPlcyDetail/20260327005400212304",
      "source": "온통청년",
      "region": "전국",
      "is_new": false
    },
    {
      "id": "youth_a9f77dcfa2",
      "category": "지원금",
      "subcategory": "주거지원",
      "title": "청년인큐베이팅공유공간 운영",
      "org": "경상북도 의성군 관광복지국",
      "deadline": "2026-12-31",
      "url": "https://www.youthcenter.go.kr/youthPolicy/ythPlcyTotalSearch/ythPlcyDetail/20260330005400212325",
      "source": "온통청년",
      "region": "부산",
      "is_new": false
    },
    {
      "id": "youth_59d0cf61e2",
      "category": "지원금",
      "subcategory": "취업지원",
      "title": "청년일자리 도전 지원사업",
      "org": "경상남도",
      "deadline": "2026-12-31",
      "url": "https://www.youthcenter.go.kr/youthPolicy/ythPlcyTotalSearch/ythPlcyDetail/20260408005400212579",
      "source": "온통청년",
      "region": "전국",
      "is_new": false
    },
    {
      "id": "youth_fabf885108",
      "category": "지원금",
      "subcategory": "취업지원",
      "title": "청년일자리 로컬 솔루션 프로젝트",
      "org": "경상북도 경주시 시민복지국",
      "deadline": "2026-12-31",
      "url": "https://www.youthcenter.go.kr/youthPolicy/ythPlcyTotalSearch/ythPlcyDetail/20260313005400212120",
      "source": "온통청년",
      "region": "전국",
      "is_new": false
    },
    {
      "id": "youth_0597e75ff4",
      "category": "지원금",
      "subcategory": "지원사업",
      "title": "청년층 자살시도자 치료비 지원사업",
      "org": "제주특별자치도경제통상진흥원 경영본부 청년센터",
      "deadline": "2026-12-31",
      "url": "https://www.youthcenter.go.kr/youthPolicy/ythPlcyTotalSearch/ythPlcyDetail/20260421005400212802",
      "source": "온통청년",
      "region": "전국",
      "amount": "최대 100만원",
      "is_new": false
    },
    {
      "id": "youth_713d591005",
      "category": "지원금",
      "subcategory": "주거지원",
      "title": "청년키움지원센터 운영",
      "org": "경상북도 의성군 관광복지국",
      "deadline": "2026-12-31",
      "url": "https://www.youthcenter.go.kr/youthPolicy/ythPlcyTotalSearch/ythPlcyDetail/20260330005400212324",
      "source": "온통청년",
      "region": "부산",
      "is_new": false
    },
    {
      "id": "youth_eb04c34c60",
      "category": "지원금",
      "subcategory": "지원사업",
      "title": "청년한부모 자녀양육비 지원",
      "org": "경상북도",
      "deadline": "2026-12-31",
      "url": "https://www.youthcenter.go.kr/youthPolicy/ythPlcyTotalSearch/ythPlcyDetail/20260317005400212183",
      "source": "온통청년",
      "region": "전국",
      "is_new": false
    },
    {
      "id": "youth_59484e78f5",
      "category": "지원금",
      "subcategory": "지원사업",
      "title": "청소년쉼터 퇴소 청소년 자립지원수당 지원",
      "org": "제주특별자치도경제통상진흥원 경영본부 청년센터",
      "deadline": "2026-12-31",
      "url": "https://www.youthcenter.go.kr/youthPolicy/ythPlcyTotalSearch/ythPlcyDetail/20260421005400212776",
      "source": "온통청년",
      "region": "전국",
      "amount": "월 50만원",
      "is_new": false
    },
    {
      "id": "youth_5faa6fdc3f",
      "category": "지원금",
      "subcategory": "취업지원",
      "title": "청소년한부모 자립 지원사업",
      "org": "울산광역시 기업투자국",
      "deadline": "2026-12-31",
      "url": "https://www.youthcenter.go.kr/youthPolicy/ythPlcyTotalSearch/ythPlcyDetail/20260410005400212681",
      "source": "온통청년",
      "region": "전국",
      "amount": "월 37만원",
      "is_new": false
    },
    {
      "id": "youth_0a40264257",
      "category": "지원금",
      "subcategory": "주거지원",
      "title": "청춘가 청년주거지 운영",
      "org": "경상북도 의성군 관광복지국",
      "deadline": "2026-12-31",
      "url": "https://www.youthcenter.go.kr/youthPolicy/ythPlcyTotalSearch/ythPlcyDetail/20260325005400212274",
      "source": "온통청년",
      "region": "전국",
      "is_new": false
    },
    {
      "id": "youth_34c12eca91",
      "category": "지원금",
      "subcategory": "주거지원",
      "title": "청춘어람 운영",
      "org": "경상북도 의성군 관광복지국",
      "deadline": "2026-12-31",
      "url": "https://www.youthcenter.go.kr/youthPolicy/ythPlcyTotalSearch/ythPlcyDetail/20260330005400212322",
      "source": "온통청년",
      "region": "부산",
      "is_new": false
    },
    {
      "id": "youth_bf3479feb8",
      "category": "지원금",
      "subcategory": "지원사업",
      "title": "출산장려금 지원",
      "org": "경상북도 의성군 관광복지국",
      "deadline": "2026-12-31",
      "url": "https://www.youthcenter.go.kr/youthPolicy/ythPlcyTotalSearch/ythPlcyDetail/20260330005400212327",
      "source": "온통청년",
      "region": "전국",
      "amount": "월30만원",
      "is_new": false
    },
    {
      "id": "youth_075c02115b",
      "category": "지원금",
      "subcategory": "창업지원",
      "title": "탐나는 디지털 창작소 운영사업",
      "org": "제주특별자치도경제통상진흥원 경영본부 청년센터",
      "deadline": "2026-12-31",
      "url": "https://www.youthcenter.go.kr/youthPolicy/ythPlcyTotalSearch/ythPlcyDetail/20260416005400212752",
      "source": "온통청년",
      "region": "전국",
      "is_new": false
    },
    {
      "id": "youth_2b4654bac7",
      "category": "지원금",
      "subcategory": "취업지원",
      "title": "직업교육 혁신지구 지원사업",
      "org": "(재)경상북도경제진흥원",
      "deadline": "2027-02-28",
      "url": "https://www.youthcenter.go.kr/youthPolicy/ythPlcyTotalSearch/ythPlcyDetail/20260313005400212128",
      "source": "온통청년",
      "region": "전국",
      "is_new": false
    },
    {
      "id": "youth_1760cf098e",
      "category": "지원금",
      "subcategory": "지원사업",
      "title": "중견기업-지역 혁신 얼라이언스 지원사업",
      "org": "경상남도",
      "deadline": "2027-12-31",
      "url": "https://www.youthcenter.go.kr/youthPolicy/ythPlcyTotalSearch/ythPlcyDetail/20260408005400212642",
      "source": "온통청년",
      "region": "전국",
      "is_new": false
    },
    {
      "id": "youth_c3e9c4a960",
      "category": "지원금",
      "subcategory": "지원사업",
      "title": "제5차 해운항만물류 전문인력 양성사업",
      "org": "경상남도",
      "deadline": "2029-12-31",
      "url": "https://www.youthcenter.go.kr/youthPolicy/ythPlcyTotalSearch/ythPlcyDetail/20260408005400212584",
      "source": "온통청년",
      "region": "전국",
      "is_new": false
    },
    {
      "id": "youth_b830b9aa94",
      "category": "지원금",
      "subcategory": "생활지원",
      "title": "청년농업인 영농정착지원",
      "org": "경상남도",
      "deadline": "2030-12-31",
      "url": "https://www.youthcenter.go.kr/youthPolicy/ythPlcyTotalSearch/ythPlcyDetail/20260408005400212643",
      "source": "온통청년",
      "region": "전국",
      "amount": "월 최대 110만원",
      "is_new": false
    }
  ]
}
